{
  "version": 2,
  "projects": [
    {
      "fieldConfig": {
        "hacknight": {
          "richText": true
        },
        "slackChannel": {
          "richText": true
        },
        "archive_status": {
          "options": [
            "backlog",
            "discovering",
            "reviewing",
            "published",
            "archived"
          ]
        },
        "community_status": {
          "options": [
            "unknown",
            "open/new",
            "open/dormant",
            "open/active",
            "closed/graduated",
            "closed/completed",
            "closed/abandoned"
          ]
        },
        "feature": {},
        "website": {
          "richText": true
        }
      },
      "defaultName": "",
      "templates": [],
      "excludedNotes": [],
      "isDefault": false,
      "dataSource": {
        "kind": "folder",
        "config": {
          "path": "_projects",
          "recursive": false
        }
      },
      "newNotesFolder": "",
      "views": [
        {
          "config": {
            "orderFields": [
              "name",
              "launched",
              "online",
              "feature",
              "archive_status",
              "slackChannel",
              "website",
              "community_status",
              "dateActiveFirst",
              "dateActiveLast",
              "description",
              "fromBreakout",
              "gitrepo",
              "hacknight",
              "notes",
              "social",
              "source",
              "tags",
              "url"
            ],
            "fieldConfig": {
              "description": {
                "width": 446,
                "hide": false
              },
              "path": {
                "hide": true
              },
              "dateActiveFirst": {
                "hide": false
              },
              "dateActiveLast": {
                "hide": false
              },
              "fromBreakout": {
                "hide": false
              },
              "github": {
                "hide": true
              },
              "hacknight": {
                "hide": false
              },
              "notes": {
                "hide": false
              },
              "tags": {
                "hide": false
              },
              "source": {
                "hide": false
              },
              "social_twitter": {
                "hide": true
              },
              "social_instagram": {
                "hide": true
              },
              "gitrepo": {
                "hide": false
              },
              "name": {
                "width": 452
              }
            }
          },
          "filter": {
            "conjunction": "and",
            "conditions": []
          },
          "colors": {
            "conditions": [
              {
                "color": "#80ff88",
                "condition": {
                  "field": "fromBreakout",
                  "operator": "is-checked",
                  "enabled": true,
                  "value": "true"
                }
              }
            ]
          },
          "sort": {
            "criteria": [
              {
                "field": "online",
                "order": "desc",
                "enabled": true
              },
              {
                "field": "path",
                "order": "asc",
                "enabled": true
              },
              {
                "field": "online",
                "order": "desc",
                "enabled": true
              }
            ]
          },
          "id": "9d08d378-8d9a-4768-b164-75903f872294",
          "name": "Table",
          "type": "table"
        },
        {
          "config": {
            "includeFields": [
              "slackChannel",
              "hacknight"
            ],
            "groupByField": "status_archive"
          },
          "filter": {
            "conjunction": "and",
            "conditions": [
              {
                "field": "fromBreakout",
                "operator": "is-checked",
                "enabled": true
              }
            ]
          },
          "colors": {
            "conditions": [
              {
                "color": "#fff480",
                "condition": {
                  "field": "showCase",
                  "operator": "is-checked",
                  "enabled": true
                }
              }
            ]
          },
          "sort": {
            "criteria": [
              {
                "field": "showCase",
                "order": "desc",
                "enabled": true
              }
            ]
          },
          "id": "12d3918f-3770-406d-b5e4-efa54ae2d409",
          "name": "Archive Tracking",
          "type": "board"
        },
        {
          "config": {
            "includeFields": [
              "slackChannel",
              "website"
            ],
            "groupByField": "status_community",
            "columns": {
              "unknown": {
                "weight": 0
              },
              "open/dormant": {
                "weight": 1
              },
              "open/active": {
                "weight": 2
              },
              "closed/graduated": {
                "weight": 3
              },
              "closed/completed": {
                "weight": 4
              },
              "closed/abandoned": {
                "weight": 5
              }
            }
          },
          "filter": {
            "conjunction": "and",
            "conditions": [
              {
                "field": "fromBreakout",
                "operator": "is-checked",
                "enabled": true
              }
            ]
          },
          "colors": {
            "conditions": []
          },
          "sort": {
            "criteria": [
              {
                "field": "name",
                "order": "asc",
                "enabled": true
              }
            ]
          },
          "id": "7a30f33e-441c-44b7-be50-84828839941f",
          "name": "Community Tracking",
          "type": "board"
        }
      ],
      "id": "7accd639-5298-44f6-8ab2-c91ee772e78f",
      "name": "projects"
    },
    {
      "fieldConfig": {},
      "defaultName": "",
      "templates": [
        "utilities/templates/template-hacknight.md"
      ],
      "excludedNotes": [],
      "isDefault": true,
      "dataSource": {
        "kind": "folder",
        "config": {
          "path": "_hacknights",
          "recursive": false
        }
      },
      "newNotesFolder": "",
      "views": [
        {
          "config": {
            "fieldConfig": {
              "path": {
                "hide": true
              },
              "booker": {
                "hide": true
              },
              "topic": {
                "width": 549,
                "hide": false
              },
              "description": {
                "width": 965,
                "hide": true
              },
              "name": {
                "width": 206,
                "hide": false
              },
              "eventUrl": {
                "hide": true
              },
              "date": {
                "hide": false
              },
              "number": {
                "hide": true
              },
              "tags": {
                "hide": true
              },
              "videoUrl": {
                "hide": false
              },
              "via": {
                "hide": true
              },
              "venue": {
                "hide": true
              },
              "speakers": {
                "width": 230,
                "hide": false
              },
              "image": {
                "hide": true
              }
            },
            "orderFields": [
              "name",
              "topic",
              "description"
            ]
          },
          "filter": {
            "conjunction": "and",
            "conditions": [
              {
                "field": "date",
                "operator": "is-after",
                "enabled": false,
                "value": "2019-12-31"
              },
              {
                "field": "date",
                "operator": "is-before",
                "enabled": false,
                "value": "2021-01-01"
              },
              {
                "field": "videoUrl",
                "operator": "is-not-empty",
                "enabled": false
              }
            ]
          },
          "colors": {
            "conditions": []
          },
          "sort": {
            "criteria": [
              {
                "field": "name",
                "order": "asc",
                "enabled": true
              }
            ]
          },
          "id": "4293c1f7-9331-473f-8d17-be23760fcf31",
          "name": "Table",
          "type": "table"
        },
        {
          "config": {
            "interval": "month"
          },
          "filter": {
            "conjunction": "and",
            "conditions": []
          },
          "colors": {
            "conditions": []
          },
          "sort": {
            "criteria": []
          },
          "id": "3f23e2d7-248f-4474-986f-83809f6d12cc",
          "name": "Calendar",
          "type": "calendar"
        },
        {
          "config": {
            "coverField": "image",
            "includeFields": [
              "speakers",
              "venue"
            ]
          },
          "filter": {
            "conjunction": "and",
            "conditions": [
              {
                "field": "image",
                "operator": "is-not-empty",
                "enabled": false
              },
              {
                "field": "venue",
                "operator": "is",
                "enabled": false,
                "value": "[[venues/Lighthouse Labs]]"
              }
            ]
          },
          "colors": {
            "conditions": []
          },
          "sort": {
            "criteria": []
          },
          "id": "3fd886cb-47b0-411c-89d0-23d3e7aa58eb",
          "name": "Gallery",
          "type": "gallery"
        }
      ],
      "id": "e1583211-52e5-4b94-8711-5245de8e6c26",
      "name": "hacknights"
    },
    {
      "fieldConfig": {
        "organization": {
          "richText": true
        }
      },
      "defaultName": "",
      "templates": [],
      "excludedNotes": [],
      "isDefault": false,
      "dataSource": {
        "kind": "folder",
        "config": {
          "path": "_people",
          "recursive": false
        }
      },
      "newNotesFolder": "",
      "views": [
        {
          "config": {
            "orderFields": [
              "name",
              "description",
              "title",
              "organization",
              "tags",
              "social",
              "project"
            ],
            "fieldConfig": {
              "path": {
                "hide": true
              },
              "social": {
                "hide": true
              },
              "tags": {
                "hide": false
              },
              "organization": {
                "hide": false,
                "width": 215
              },
              "title": {
                "hide": false,
                "width": 398
              },
              "url": {
                "hide": false
              },
              "description": {
                "hide": false,
                "width": 729
              },
              "project": {
                "hide": true,
                "width": 232
              },
              "aliases": {
                "hide": true
              }
            }
          },
          "filter": {
            "conjunction": "and",
            "conditions": [
              {
                "field": "tags",
                "operator": "has-keyword",
                "enabled": true,
                "value": "speaker"
              },
              {
                "field": "description",
                "operator": "contains",
                "enabled": false,
                "value": "\""
              }
            ]
          },
          "colors": {
            "conditions": []
          },
          "sort": {
            "criteria": []
          },
          "id": "6d021da1-75af-4070-815d-394f9793e71d",
          "name": "Table",
          "type": "table"
        }
      ],
      "id": "b6fbcab0-c3ed-46f1-b3fa-41b6060b7170",
      "name": "people"
    },
    {
      "fieldConfig": {
        "parent_organization": {
          "richText": true
        }
      },
      "defaultName": "",
      "templates": [
        "utilities/templates/template-organization.md"
      ],
      "excludedNotes": [],
      "isDefault": false,
      "dataSource": {
        "kind": "folder",
        "config": {
          "path": "_organizations",
          "recursive": false
        }
      },
      "newNotesFolder": "",
      "views": [
        {
          "config": {
            "fieldConfig": {
              "tags": {
                "width": 586
              },
              "name": {
                "width": 367
              }
            }
          },
          "filter": {
            "conjunction": "and",
            "conditions": []
          },
          "colors": {
            "conditions": []
          },
          "sort": {
            "criteria": []
          },
          "id": "d46af66a-9df6-4653-9f07-00b039213c19",
          "name": "Table",
          "type": "table"
        },
        {
          "config": {
            "coverField": "image"
          },
          "filter": {
            "conjunction": "and",
            "conditions": [
              {
                "field": "image",
                "operator": "is-not-empty",
                "enabled": true
              }
            ]
          },
          "colors": {
            "conditions": []
          },
          "sort": {
            "criteria": []
          },
          "id": "e1bbfaa0-f061-4c96-b59f-2ac5f7e24ed4",
          "name": "Gallery",
          "type": "gallery"
        }
      ],
      "id": "e4b12e2a-41a2-41db-88fa-94a9c682a285",
      "name": "organizations"
    },
    {
      "fieldConfig": {},
      "defaultName": "",
      "templates": [],
      "excludedNotes": [],
      "isDefault": false,
      "dataSource": {
        "kind": "folder",
        "config": {
          "path": "_venues",
          "recursive": false
        }
      },
      "newNotesFolder": "",
      "views": [
        {
          "config": {
            "orderFields": [
              "path",
              "name",
              "address",
              "organization",
              "status",
              "tags",
              "type"
            ],
            "fieldConfig": {
              "path": {
                "hide": true
              },
              "organization": {
                "hide": true
              },
              "status": {
                "hide": true
              },
              "type": {
                "hide": true
              },
              "tags": {
                "hide": true
              },
              "address": {
                "width": 378
              },
              "name": {
                "width": 320
              }
            }
          },
          "filter": {
            "conjunction": "and",
            "conditions": []
          },
          "colors": {
            "conditions": []
          },
          "sort": {
            "criteria": []
          },
          "id": "f3aeecb2-5304-47fc-887a-222a78258a61",
          "name": "Table",
          "type": "table"
        }
      ],
      "id": "5050ab6a-67cd-47b5-8a07-02f3ecc31506",
      "name": "venues"
    },
    {
      "fieldConfig": {},
      "defaultName": "",
      "templates": [],
      "excludedNotes": [],
      "isDefault": false,
      "dataSource": {
        "kind": "folder",
        "config": {
          "path": "_venues",
          "recursive": false
        }
      },
      "newNotesFolder": "",
      "views": [
        {
          "config": {},
          "filter": {
            "conjunction": "and",
            "conditions": []
          },
          "colors": {
            "conditions": []
          },
          "sort": {
            "criteria": []
          },
          "id": "6a6f8863-6df0-4209-a3c5-23c41e5edca1",
          "name": "Table",
          "type": "table"
        }
      ],
      "id": "0f182b17-a6c3-4be1-8d7e-4cb378e5cc8a",
      "name": "venue"
    }
  ],
  "archives": [],
  "preferences": {
    "projectSizeLimit": 1000,
    "frontmatter": {
      "quoteStrings": "PLAIN"
    },
    "locale": {
      "firstDayOfWeek": "default"
    },
    "commands": [],
    "linkBehavior": "open-editor"
  }
}